odoo/addons/beesdoo_account/README.rst
odoo/addons/beesdoo_account/__init__.py
odoo/addons/beesdoo_account/__manifest__.py
odoo/addons/beesdoo_account/i18n/beesdoo_account.pot
odoo/addons/beesdoo_account/i18n/fr.po
odoo/addons/beesdoo_account/i18n/fr_BE.po
odoo/addons/beesdoo_account/i18n/fr_CH.po
odoo/addons/beesdoo_account/models/__init__.py
odoo/addons/beesdoo_account/models/account_invoice.py
odoo/addons/beesdoo_account/models/res_config.py
odoo/addons/beesdoo_account/readme/CONFIGURE.rst
odoo/addons/beesdoo_account/readme/CONTRIBUTORS.rst
odoo/addons/beesdoo_account/readme/DESCRIPTION.rst
odoo/addons/beesdoo_account/security/invoice_security.xml
odoo/addons/beesdoo_account/static/description/index.html
odoo/addons/beesdoo_account/views/account_invoice.xml
odoo/addons/beesdoo_account/views/res_config_view.xml
odoo12_addon_beesdoo_account-12.0.1.1.0.99.dev12.dist-info/METADATA
odoo12_addon_beesdoo_account-12.0.1.1.0.99.dev12.dist-info/WHEEL
odoo12_addon_beesdoo_account-12.0.1.1.0.99.dev12.dist-info/top_level.txt
odoo12_addon_beesdoo_account-12.0.1.1.0.99.dev12.dist-info/RECORD
